{
  "2023-05-29 - Game 1": [
    {
      "club_name": "Dewa United Esports",
      "short_name": "DEWA",
      "poin": 1,
      "score": 1,
      "score_komulatif": 1
    },
    {
      "club_name": "Geek Fam ID",
      "short_name": "GEEK",
      "poin": 0,
      "score": 0,
      "score_komulatif": 0
    },
    {
      "date": "2023-05-29",
      "time": "19:00",
      "result": {
        "score_split": "1:0",
        "score_komulatif": "0:1",
        "score_fixed": "1:2"
      },
      "league": "Snapdragon Pro Series Season 3 SEA - Open Finals",
      "clubs": [
        "DEWA",
        "GEEK"
      ]
    }
  ],
  "2023-05-29 - Game 2": [
    {
      "club_name": "Dewa United Esports",
      "short_name": "DEWA",
      "poin": 1,
      "score": 0,
      "score_komulatif": 1
    },
    {
      "club_name": "Geek Fam ID",
      "short_name": "GEEK",
      "poin": 1,
      "score": 1,
      "score_komulatif": 1
    },
    {
      "date": "2023-05-29",
      "time": "19:00",
      "result": {
        "score_split": "0:1",
        "score_komulatif": "1:1",
        "score_fixed": "1:2"
      },
      "league": "Snapdragon Pro Series Season 3 SEA - Open Finals",
      "clubs": [
        "DEWA",
        "GEEK"
      ]
    }
  ],
  "2023-05-29 - Game 3": [
    {
      "club_name": "Dewa United Esports",
      "short_name": "DEWA",
      "poin": 2,
      "score": 1,
      "score_komulatif": 2
    },
    {
      "club_name": "Geek Fam ID",
      "short_name": "GEEK",
      "poin": 1,
      "score": 0,
      "score_komulatif": 1
    },
    {
      "date": "2023-05-29",
      "time": "19:00",
      "result": {
        "score_split": "1:0",
        "score_komulatif": "1:2",
        "score_fixed": "1:2"
      },
      "league": "Snapdragon Pro Series Season 3 SEA - Open Finals",
      "clubs": [
        "DEWA",
        "GEEK"
      ]
    }
  ],
  "2023-08-04 - Game 1": [
    {
      "club_name": "Dewa United Esports",
      "short_name": "DEWA",
      "poin": 3,
      "score": 1,
      "score_komulatif": 1
    },
    {
      "club_name": "Geek Fam ID",
      "short_name": "GEEK",
      "poin": 1,
      "score": 0,
      "score_komulatif": 0
    },
    {
      "date": "2023-08-04",
      "time": "19:00",
      "result": {
        "score_split": "1:0",
        "score_komulatif": "0:1",
        "score_fixed": "0:2"
      },
      "league": "MPL ID Season 12 - Regular Season",
      "clubs": [
        "DEWA",
        "GEEK"
      ]
    }
  ],
  "2023-08-04 - Game 2": [
    {
      "club_name": "Dewa United Esports",
      "short_name": "DEWA",
      "poin": 4,
      "score": 1,
      "score_komulatif": 2
    },
    {
      "club_name": "Geek Fam ID",
      "short_name": "GEEK",
      "poin": 1,
      "score": 0,
      "score_komulatif": 0
    },
    {
      "date": "2023-08-04",
      "time": "19:00",
      "result": {
        "score_split": "1:0",
        "score_komulatif": "0:2",
        "score_fixed": "0:2"
      },
      "league": "MPL ID Season 12 - Regular Season",
      "clubs": [
        "DEWA",
        "GEEK"
      ]
    }
  ],
  "2023-09-15 - Game 1": [
    {
      "club_name": "Dewa United Esports",
      "short_name": "DEWA",
      "poin": 5,
      "score": 1,
      "score_komulatif": 1
    },
    {
      "club_name": "Geek Fam ID",
      "short_name": "GEEK",
      "poin": 1,
      "score": 0,
      "score_komulatif": 0
    },
    {
      "date": "2023-09-15",
      "time": "19:00",
      "result": {
        "score_split": "1:0",
        "score_komulatif": "0:1",
        "score_fixed": "0:2"
      },
      "league": "MPL ID Season 12 - Regular Season",
      "clubs": [
        "DEWA",
        "GEEK"
      ]
    }
  ],
  "2023-09-15 - Game 2": [
    {
      "club_name": "Dewa United Esports",
      "short_name": "DEWA",
      "poin": 6,
      "score": 1,
      "score_komulatif": 2
    },
    {
      "club_name": "Geek Fam ID",
      "short_name": "GEEK",
      "poin": 1,
      "score": 0,
      "score_komulatif": 0
    },
    {
      "date": "2023-09-15",
      "time": "19:00",
      "result": {
        "score_split": "1:0",
        "score_komulatif": "0:2",
        "score_fixed": "0:2"
      },
      "league": "MPL ID Season 12 - Regular Season",
      "clubs": [
        "DEWA",
        "GEEK"
      ]
    }
  ],
  "2023-10-11 - Game 1": [
    {
      "club_name": "Dewa United Esports",
      "short_name": "DEWA",
      "poin": 6,
      "score": 0,
      "score_komulatif": 0
    },
    {
      "club_name": "Geek Fam ID",
      "short_name": "GEEK",
      "poin": 2,
      "score": 1,
      "score_komulatif": 1
    },
    {
      "date": "2023-10-11",
      "time": "19:00",
      "result": {
        "score_split": "0:1",
        "score_komulatif": "1:0",
        "score_fixed": "3:1"
      },
      "league": "MPL ID Season 12 - Playoffs",
      "clubs": [
        "DEWA",
        "GEEK"
      ]
    }
  ],
  "2023-10-11 - Game 2": [
    {
      "club_name": "Dewa United Esports",
      "short_name": "DEWA",
      "poin": 7,
      "score": 1,
      "score_komulatif": 1
    },
    {
      "club_name": "Geek Fam ID",
      "short_name": "GEEK",
      "poin": 2,
      "score": 0,
      "score_komulatif": 1
    },
    {
      "date": "2023-10-11",
      "time": "19:00",
      "result": {
        "score_split": "1:0",
        "score_komulatif": "1:1",
        "score_fixed": "3:1"
      },
      "league": "MPL ID Season 12 - Playoffs",
      "clubs": [
        "DEWA",
        "GEEK"
      ]
    }
  ],
  "2023-10-11 - Game 3": [
    {
      "club_name": "Dewa United Esports",
      "short_name": "DEWA",
      "poin": 7,
      "score": 0,
      "score_komulatif": 1
    },
    {
      "club_name": "Geek Fam ID",
      "short_name": "GEEK",
      "poin": 3,
      "score": 1,
      "score_komulatif": 2
    },
    {
      "date": "2023-10-11",
      "time": "19:00",
      "result": {
        "score_split": "0:1",
        "score_komulatif": "2:1",
        "score_fixed": "3:1"
      },
      "league": "MPL ID Season 12 - Playoffs",
      "clubs": [
        "DEWA",
        "GEEK"
      ]
    }
  ],
  "2023-10-11 - Game 4": [
    {
      "club_name": "Dewa United Esports",
      "short_name": "DEWA",
      "poin": 7,
      "score": 0,
      "score_komulatif": 1
    },
    {
      "club_name": "Geek Fam ID",
      "short_name": "GEEK",
      "poin": 4,
      "score": 1,
      "score_komulatif": 3
    },
    {
      "date": "2023-10-11",
      "time": "19:00",
      "result": {
        "score_split": "0:1",
        "score_komulatif": "3:1",
        "score_fixed": "3:1"
      },
      "league": "MPL ID Season 12 - Playoffs",
      "clubs": [
        "DEWA",
        "GEEK"
      ]
    }
  ],
  "2024-03-24 - Game 1": [
    {
      "club_name": "Dewa United Esports",
      "short_name": "DEWA",
      "poin": 8,
      "score": 1,
      "score_komulatif": 1
    },
    {
      "club_name": "Geek Fam ID",
      "short_name": "GEEK",
      "poin": 4,
      "score": 0,
      "score_komulatif": 0
    },
    {
      "date": "2024-03-24",
      "time": "19:00",
      "result": {
        "score_split": "1:0",
        "score_komulatif": "0:1",
        "score_fixed": "2:1"
      },
      "league": "MPL ID Season 13 - Regular Season",
      "clubs": [
        "DEWA",
        "GEEK"
      ]
    }
  ],
  "2024-03-24 - Game 2": [
    {
      "club_name": "Dewa United Esports",
      "short_name": "DEWA",
      "poin": 8,
      "score": 0,
      "score_komulatif": 1
    },
    {
      "club_name": "Geek Fam ID",
      "short_name": "GEEK",
      "poin": 5,
      "score": 1,
      "score_komulatif": 1
    },
    {
      "date": "2024-03-24",
      "time": "19:00",
      "result": {
        "score_split": "0:1",
        "score_komulatif": "1:1",
        "score_fixed": "2:1"
      },
      "league": "MPL ID Season 13 - Regular Season",
      "clubs": [
        "DEWA",
        "GEEK"
      ]
    }
  ],
  "2024-03-24 - Game 3": [
    {
      "club_name": "Dewa United Esports",
      "short_name": "DEWA",
      "poin": 8,
      "score": 0,
      "score_komulatif": 1
    },
    {
      "club_name": "Geek Fam ID",
      "short_name": "GEEK",
      "poin": 6,
      "score": 1,
      "score_komulatif": 2
    },
    {
      "date": "2024-03-24",
      "time": "19:00",
      "result": {
        "score_split": "0:1",
        "score_komulatif": "2:1",
        "score_fixed": "2:1"
      },
      "league": "MPL ID Season 13 - Regular Season",
      "clubs": [
        "DEWA",
        "GEEK"
      ]
    }
  ],
  "2024-05-10 - Game 1": [
    {
      "club_name": "Dewa United Esports",
      "short_name": "DEWA",
      "poin": 8,
      "score": 0,
      "score_komulatif": 0
    },
    {
      "club_name": "Geek Fam ID",
      "short_name": "GEEK",
      "poin": 7,
      "score": 1,
      "score_komulatif": 1
    },
    {
      "date": "2024-05-10",
      "time": "19:00",
      "result": {
        "score_split": "0:1",
        "score_komulatif": "1:0",
        "score_fixed": "2:1"
      },
      "league": "MPL ID Season 13 - Regular Season",
      "clubs": [
        "DEWA",
        "GEEK"
      ]
    }
  ],
  "2024-05-10 - Game 2": [
    {
      "club_name": "Dewa United Esports",
      "short_name": "DEWA",
      "poin": 9,
      "score": 1,
      "score_komulatif": 1
    },
    {
      "club_name": "Geek Fam ID",
      "short_name": "GEEK",
      "poin": 7,
      "score": 0,
      "score_komulatif": 1
    },
    {
      "date": "2024-05-10",
      "time": "19:00",
      "result": {
        "score_split": "1:0",
        "score_komulatif": "1:1",
        "score_fixed": "2:1"
      },
      "league": "MPL ID Season 13 - Regular Season",
      "clubs": [
        "DEWA",
        "GEEK"
      ]
    }
  ],
  "2024-05-10 - Game 3": [
    {
      "club_name": "Dewa United Esports",
      "short_name": "DEWA",
      "poin": 9,
      "score": 0,
      "score_komulatif": 1
    },
    {
      "club_name": "Geek Fam ID",
      "short_name": "GEEK",
      "poin": 8,
      "score": 1,
      "score_komulatif": 2
    },
    {
      "date": "2024-05-10",
      "time": "19:00",
      "result": {
        "score_split": "0:1",
        "score_komulatif": "2:1",
        "score_fixed": "2:1"
      },
      "league": "MPL ID Season 13 - Regular Season",
      "clubs": [
        "DEWA",
        "GEEK"
      ]
    }
  ],
  "2024-08-11 - Game 1": [
    {
      "club_name": "Dewa United Esports",
      "short_name": "DEWA",
      "poin": 10,
      "score": 1,
      "score_komulatif": 1
    },
    {
      "club_name": "Geek Fam ID",
      "short_name": "GEEK",
      "poin": 8,
      "score": 0,
      "score_komulatif": 0
    },
    {
      "date": "2024-08-11",
      "time": "19:00",
      "result": {
        "score_split": "1:0",
        "score_komulatif": "0:1",
        "score_fixed": "0:2"
      },
      "league": "MPL ID Season 14 - Regular Season",
      "clubs": [
        "DEWA",
        "GEEK"
      ]
    }
  ],
  "2024-08-11 - Game 2": [
    {
      "club_name": "Dewa United Esports",
      "short_name": "DEWA",
      "poin": 11,
      "score": 1,
      "score_komulatif": 2
    },
    {
      "club_name": "Geek Fam ID",
      "short_name": "GEEK",
      "poin": 8,
      "score": 0,
      "score_komulatif": 0
    },
    {
      "date": "2024-08-11",
      "time": "19:00",
      "result": {
        "score_split": "1:0",
        "score_komulatif": "0:2",
        "score_fixed": "0:2"
      },
      "league": "MPL ID Season 14 - Regular Season",
      "clubs": [
        "DEWA",
        "GEEK"
      ]
    }
  ],
  "2024-09-20 - Game 1": [
    {
      "club_name": "Dewa United Esports",
      "short_name": "DEWA",
      "poin": 11,
      "score": 0,
      "score_komulatif": 0
    },
    {
      "club_name": "Geek Fam ID",
      "short_name": "GEEK",
      "poin": 9,
      "score": 1,
      "score_komulatif": 1
    },
    {
      "date": "2024-09-20",
      "time": "19:00",
      "result": {
        "score_split": "0:1",
        "score_komulatif": "1:0",
        "score_fixed": "2:0"
      },
      "league": "MPL ID Season 14 - Regular Season",
      "clubs": [
        "DEWA",
        "GEEK"
      ]
    }
  ],
  "2024-09-20 - Game 2": [
    {
      "club_name": "Dewa United Esports",
      "short_name": "DEWA",
      "poin": 11,
      "score": 0,
      "score_komulatif": 0
    },
    {
      "club_name": "Geek Fam ID",
      "short_name": "GEEK",
      "poin": 10,
      "score": 1,
      "score_komulatif": 2
    },
    {
      "date": "2024-09-20",
      "time": "19:00",
      "result": {
        "score_split": "0:1",
        "score_komulatif": "2:0",
        "score_fixed": "2:0"
      },
      "league": "MPL ID Season 14 - Regular Season",
      "clubs": [
        "DEWA",
        "GEEK"
      ]
    }
  ],
  "2025-04-20 - Game 1": [
    {
      "club_name": "Dewa United Esports",
      "short_name": "DEWA",
      "poin": 11,
      "score": 0,
      "score_komulatif": 0
    },
    {
      "club_name": "Geek Fam ID",
      "short_name": "GEEK",
      "poin": 11,
      "score": 1,
      "score_komulatif": 1
    },
    {
      "date": "2025-04-20",
      "time": "19:00",
      "result": {
        "score_split": "0:1",
        "score_komulatif": "1:0",
        "score_fixed": "2:1"
      },
      "league": "MPL ID Season 15 - Regular Season",
      "clubs": [
        "DEWA",
        "GEEK"
      ]
    }
  ],
  "2025-04-20 - Game 2": [
    {
      "club_name": "Dewa United Esports",
      "short_name": "DEWA",
      "poin": 12,
      "score": 1,
      "score_komulatif": 1
    },
    {
      "club_name": "Geek Fam ID",
      "short_name": "GEEK",
      "poin": 11,
      "score": 0,
      "score_komulatif": 1
    },
    {
      "date": "2025-04-20",
      "time": "19:00",
      "result": {
        "score_split": "1:0",
        "score_komulatif": "1:1",
        "score_fixed": "2:1"
      },
      "league": "MPL ID Season 15 - Regular Season",
      "clubs": [
        "DEWA",
        "GEEK"
      ]
    }
  ],
  "2025-04-20 - Game 3": [
    {
      "club_name": "Dewa United Esports",
      "short_name": "DEWA",
      "poin": 12,
      "score": 0,
      "score_komulatif": 1
    },
    {
      "club_name": "Geek Fam ID",
      "short_name": "GEEK",
      "poin": 12,
      "score": 1,
      "score_komulatif": 2
    },
    {
      "date": "2025-04-20",
      "time": "19:00",
      "result": {
        "score_split": "0:1",
        "score_komulatif": "2:1",
        "score_fixed": "2:1"
      },
      "league": "MPL ID Season 15 - Regular Season",
      "clubs": [
        "DEWA",
        "GEEK"
      ]
    }
  ]
}