{
  "1931-09-27": [
    {
      "club_name": "CS Cagliari",
      "short_name": "CAG",
      "poin": 1,
      "score": 1
    },
    {
      "club_name": "Parma FC",
      "short_name": "PAR",
      "poin": 0,
      "score": 0
    },
    {
      "club_name": "Draw",
      "short_name": "DRAW",
      "poin": 0,
      "date": "1931-09-27",
      "time": "19:00",
      "result": "0:1",
      "league": "Serie B",
      "clubs": [
        "CAG",
        "PAR"
      ]
    }
  ],
  "1932-02-07": [
    {
      "club_name": "CS Cagliari",
      "short_name": "CAG",
      "poin": 2,
      "score": 2
    },
    {
      "club_name": "Parma FC",
      "short_name": "PAR",
      "poin": 0,
      "score": 1
    },
    {
      "club_name": "Draw",
      "short_name": "DRAW",
      "poin": 0,
      "date": "1932-02-07",
      "time": "19:00",
      "result": "2:1",
      "league": "Serie B",
      "clubs": [
        "CAG",
        "PAR"
      ]
    }
  ],
  "1954-12-12": [
    {
      "club_name": "Unione Sportiva Cagliari",
      "short_name": "CAG",
      "poin": 2,
      "score": 1
    },
    {
      "club_name": "Parma FC",
      "short_name": "PAR",
      "poin": 0,
      "score": 1
    },
    {
      "club_name": "Draw",
      "short_name": "DRAW",
      "poin": 1,
      "date": "1954-12-12",
      "time": "19:00",
      "result": "1:1",
      "league": "Serie B",
      "clubs": [
        "CAG",
        "PAR"
      ]
    }
  ],
  "1955-04-24": [
    {
      "club_name": "Unione Sportiva Cagliari",
      "short_name": "CAG",
      "poin": 3,
      "score": 2
    },
    {
      "club_name": "Parma FC",
      "short_name": "PAR",
      "poin": 0,
      "score": 1
    },
    {
      "club_name": "Draw",
      "short_name": "DRAW",
      "poin": 1,
      "date": "1955-04-24",
      "time": "19:00",
      "result": "1:2",
      "league": "Serie B",
      "clubs": [
        "CAG",
        "PAR"
      ]
    }
  ],
  "1956-01-01": [
    {
      "club_name": "Unione Sportiva Cagliari",
      "short_name": "CAG",
      "poin": 3,
      "score": 0
    },
    {
      "club_name": "Parma FC",
      "short_name": "PAR",
      "poin": 1,
      "score": 1
    },
    {
      "club_name": "Draw",
      "short_name": "DRAW",
      "poin": 1,
      "date": "1956-01-01",
      "time": "19:00",
      "result": "0:1",
      "league": "Serie B",
      "clubs": [
        "CAG",
        "PAR"
      ]
    }
  ],
  "1956-05-13": [
    {
      "club_name": "Unione Sportiva Cagliari",
      "short_name": "CAG",
      "poin": 3,
      "score": 0
    },
    {
      "club_name": "Parma FC",
      "short_name": "PAR",
      "poin": 2,
      "score": 1
    },
    {
      "club_name": "Draw",
      "short_name": "DRAW",
      "poin": 1,
      "date": "1956-05-13",
      "time": "19:00",
      "result": "1:0",
      "league": "Serie B",
      "clubs": [
        "CAG",
        "PAR"
      ]
    }
  ],
  "1957-01-20": [
    {
      "club_name": "Unione Sportiva Cagliari",
      "short_name": "CAG",
      "poin": 4,
      "score": 2
    },
    {
      "club_name": "Parma FC",
      "short_name": "PAR",
      "poin": 2,
      "score": 0
    },
    {
      "club_name": "Draw",
      "short_name": "DRAW",
      "poin": 1,
      "date": "1957-01-20",
      "time": "19:00",
      "result": "2:0",
      "league": "Serie B",
      "clubs": [
        "CAG",
        "PAR"
      ]
    }
  ],
  "1957-06-09": [
    {
      "club_name": "Unione Sportiva Cagliari",
      "short_name": "CAG",
      "poin": 4,
      "score": 0
    },
    {
      "club_name": "Parma FC",
      "short_name": "PAR",
      "poin": 3,
      "score": 4
    },
    {
      "club_name": "Draw",
      "short_name": "DRAW",
      "poin": 1,
      "date": "1957-06-09",
      "time": "19:00",
      "result": "4:0",
      "league": "Serie B",
      "clubs": [
        "CAG",
        "PAR"
      ]
    }
  ],
  "1957-11-10": [
    {
      "club_name": "Unione Sportiva Cagliari",
      "short_name": "CAG",
      "poin": 5,
      "score": 2
    },
    {
      "club_name": "Parma FC",
      "short_name": "PAR",
      "poin": 3,
      "score": 0
    },
    {
      "club_name": "Draw",
      "short_name": "DRAW",
      "poin": 1,
      "date": "1957-11-10",
      "time": "19:00",
      "result": "2:0",
      "league": "Serie B",
      "clubs": [
        "CAG",
        "PAR"
      ]
    }
  ],
  "1958-03-30": [
    {
      "club_name": "Unione Sportiva Cagliari",
      "short_name": "CAG",
      "poin": 5,
      "score": 1
    },
    {
      "club_name": "Parma FC",
      "short_name": "PAR",
      "poin": 3,
      "score": 1
    },
    {
      "club_name": "Draw",
      "short_name": "DRAW",
      "poin": 2,
      "date": "1958-03-30",
      "time": "19:00",
      "result": "1:1",
      "league": "Serie B",
      "clubs": [
        "CAG",
        "PAR"
      ]
    }
  ],
  "1958-10-19": [
    {
      "club_name": "Unione Sportiva Cagliari",
      "short_name": "CAG",
      "poin": 5,
      "score": 1
    },
    {
      "club_name": "Parma FC",
      "short_name": "PAR",
      "poin": 4,
      "score": 5
    },
    {
      "club_name": "Draw",
      "short_name": "DRAW",
      "poin": 2,
      "date": "1958-10-19",
      "time": "19:00",
      "result": "5:1",
      "league": "Serie B",
      "clubs": [
        "CAG",
        "PAR"
      ]
    }
  ],
  "1959-03-08": [
    {
      "club_name": "Unione Sportiva Cagliari",
      "short_name": "CAG",
      "poin": 6,
      "score": 3
    },
    {
      "club_name": "Parma FC",
      "short_name": "PAR",
      "poin": 4,
      "score": 0
    },
    {
      "club_name": "Draw",
      "short_name": "DRAW",
      "poin": 2,
      "date": "1959-03-08",
      "time": "19:00",
      "result": "3:0",
      "league": "Serie B",
      "clubs": [
        "CAG",
        "PAR"
      ]
    }
  ],
  "1960-01-10": [
    {
      "club_name": "Unione Sportiva Cagliari",
      "short_name": "CAG",
      "poin": 7,
      "score": 2
    },
    {
      "club_name": "Parma FC",
      "short_name": "PAR",
      "poin": 4,
      "score": 0
    },
    {
      "club_name": "Draw",
      "short_name": "DRAW",
      "poin": 2,
      "date": "1960-01-10",
      "time": "19:00",
      "result": "2:0",
      "league": "Serie B",
      "clubs": [
        "CAG",
        "PAR"
      ]
    }
  ],
  "1960-05-22": [
    {
      "club_name": "Unione Sportiva Cagliari",
      "short_name": "CAG",
      "poin": 7,
      "score": 1
    },
    {
      "club_name": "Parma FC",
      "short_name": "PAR",
      "poin": 4,
      "score": 1
    },
    {
      "club_name": "Draw",
      "short_name": "DRAW",
      "poin": 3,
      "date": "1960-05-22",
      "time": "19:00",
      "result": "1:1",
      "league": "Serie B",
      "clubs": [
        "CAG",
        "PAR"
      ]
    }
  ],
  "1962-10-21": [
    {
      "club_name": "Unione Sportiva Cagliari",
      "short_name": "CAG",
      "poin": 7,
      "score": 0
    },
    {
      "club_name": "Parma FC",
      "short_name": "PAR",
      "poin": 4,
      "score": 0
    },
    {
      "club_name": "Draw",
      "short_name": "DRAW",
      "poin": 4,
      "date": "1962-10-21",
      "time": "19:00",
      "result": "0:0",
      "league": "Serie B",
      "clubs": [
        "CAG",
        "PAR"
      ]
    }
  ],
  "1963-03-10": [
    {
      "club_name": "Unione Sportiva Cagliari",
      "short_name": "CAG",
      "poin": 7,
      "score": 0
    },
    {
      "club_name": "Parma FC",
      "short_name": "PAR",
      "poin": 4,
      "score": 0
    },
    {
      "club_name": "Draw",
      "short_name": "DRAW",
      "poin": 5,
      "date": "1963-03-10",
      "time": "19:00",
      "result": "0:0",
      "league": "Serie B",
      "clubs": [
        "CAG",
        "PAR"
      ]
    }
  ],
  "1963-11-13": [
    {
      "club_name": "Unione Sportiva Cagliari",
      "short_name": "CAG",
      "poin": 8,
      "score": 2
    },
    {
      "club_name": "Parma FC",
      "short_name": "PAR",
      "poin": 4,
      "score": 1
    },
    {
      "club_name": "Draw",
      "short_name": "DRAW",
      "poin": 5,
      "date": "1963-11-13",
      "time": "19:00",
      "result": "1:2",
      "league": "Italy Cup",
      "clubs": [
        "CAG",
        "PAR"
      ]
    }
  ],
  "1964-01-05": [
    {
      "club_name": "Unione Sportiva Cagliari",
      "short_name": "CAG",
      "poin": 8,
      "score": 0
    },
    {
      "club_name": "Parma FC",
      "short_name": "PAR",
      "poin": 5,
      "score": 1
    },
    {
      "club_name": "Draw",
      "short_name": "DRAW",
      "poin": 5,
      "date": "1964-01-05",
      "time": "19:00",
      "result": "1:0",
      "league": "Serie B",
      "clubs": [
        "CAG",
        "PAR"
      ]
    }
  ],
  "1964-05-31": [
    {
      "club_name": "Unione Sportiva Cagliari",
      "short_name": "CAG",
      "poin": 9,
      "score": 2
    },
    {
      "club_name": "Parma FC",
      "short_name": "PAR",
      "poin": 5,
      "score": 0
    },
    {
      "club_name": "Draw",
      "short_name": "DRAW",
      "poin": 5,
      "date": "1964-05-31",
      "time": "19:00",
      "result": "2:0",
      "league": "Serie B",
      "clubs": [
        "CAG",
        "PAR"
      ]
    }
  ],
  "1984-12-02": [
    {
      "club_name": "Cagliari Calcio",
      "short_name": "CAG",
      "poin": 9,
      "score": 0
    },
    {
      "club_name": "AC Parma",
      "short_name": "PAR",
      "poin": 5,
      "score": 0
    },
    {
      "club_name": "Draw",
      "short_name": "DRAW",
      "poin": 6,
      "date": "1984-12-02",
      "time": "19:00",
      "result": "0:0",
      "league": "Serie B",
      "clubs": [
        "CAG",
        "PAR"
      ]
    }
  ],
  "1985-04-28": [
    {
      "club_name": "Cagliari Calcio",
      "short_name": "CAG",
      "poin": 10,
      "score": 1
    },
    {
      "club_name": "AC Parma",
      "short_name": "PAR",
      "poin": 5,
      "score": 0
    },
    {
      "club_name": "Draw",
      "short_name": "DRAW",
      "poin": 6,
      "date": "1985-04-28",
      "time": "19:00",
      "result": "1:0",
      "league": "Serie B",
      "clubs": [
        "CAG",
        "PAR"
      ]
    }
  ],
  "1986-10-26": [
    {
      "club_name": "Cagliari Calcio",
      "short_name": "CAG",
      "poin": 10,
      "score": 0
    },
    {
      "club_name": "AC Parma",
      "short_name": "PAR",
      "poin": 5,
      "score": 0
    },
    {
      "club_name": "Draw",
      "short_name": "DRAW",
      "poin": 7,
      "date": "1986-10-26",
      "time": "19:00",
      "result": "0:0",
      "league": "Serie B",
      "clubs": [
        "CAG",
        "PAR"
      ]
    }
  ],
  "1987-03-22": [
    {
      "club_name": "Cagliari Calcio",
      "short_name": "CAG",
      "poin": 10,
      "score": 1
    },
    {
      "club_name": "AC Parma",
      "short_name": "PAR",
      "poin": 5,
      "score": 1
    },
    {
      "club_name": "Draw",
      "short_name": "DRAW",
      "poin": 8,
      "date": "1987-03-22",
      "time": "19:00",
      "result": "1:1",
      "league": "Serie B",
      "clubs": [
        "CAG",
        "PAR"
      ]
    }
  ],
  "1989-11-12": [
    {
      "club_name": "Cagliari Calcio",
      "short_name": "CAG",
      "poin": 10,
      "score": 2
    },
    {
      "club_name": "AC Parma",
      "short_name": "PAR",
      "poin": 5,
      "score": 2
    },
    {
      "club_name": "Draw",
      "short_name": "DRAW",
      "poin": 9,
      "date": "1989-11-12",
      "time": "08:30",
      "result": "2:2",
      "league": "Serie B",
      "clubs": [
        "CAG",
        "PAR"
      ]
    }
  ],
  "1990-04-14": [
    {
      "club_name": "Cagliari Calcio",
      "short_name": "CAG",
      "poin": 10,
      "score": 1
    },
    {
      "club_name": "AC Parma",
      "short_name": "PAR",
      "poin": 5,
      "score": 1
    },
    {
      "club_name": "Draw",
      "short_name": "DRAW",
      "poin": 10,
      "date": "1990-04-14",
      "time": "09:30",
      "result": "1:1",
      "league": "Serie B",
      "clubs": [
        "CAG",
        "PAR"
      ]
    }
  ],
  "1990-11-25": [
    {
      "club_name": "Cagliari Calcio",
      "short_name": "CAG",
      "poin": 10,
      "score": 0
    },
    {
      "club_name": "AC Parma",
      "short_name": "PAR",
      "poin": 6,
      "score": 2
    },
    {
      "club_name": "Draw",
      "short_name": "DRAW",
      "poin": 10,
      "date": "1990-11-25",
      "time": "19:00",
      "result": "2:0",
      "league": "Serie A",
      "clubs": [
        "CAG",
        "PAR"
      ]
    }
  ],
  "1991-03-30": [
    {
      "club_name": "Cagliari Calcio",
      "short_name": "CAG",
      "poin": 11,
      "score": 2
    },
    {
      "club_name": "AC Parma",
      "short_name": "PAR",
      "poin": 6,
      "score": 1
    },
    {
      "club_name": "Draw",
      "short_name": "DRAW",
      "poin": 10,
      "date": "1991-03-30",
      "time": "19:00",
      "result": "2:1",
      "league": "Serie A",
      "clubs": [
        "CAG",
        "PAR"
      ]
    }
  ],
  "1991-11-17": [
    {
      "club_name": "Cagliari Calcio",
      "short_name": "CAG",
      "poin": 11,
      "score": 0
    },
    {
      "club_name": "AC Parma",
      "short_name": "PAR",
      "poin": 6,
      "score": 0
    },
    {
      "club_name": "Draw",
      "short_name": "DRAW",
      "poin": 11,
      "date": "1991-11-17",
      "time": "19:00",
      "result": "0:0",
      "league": "Serie A",
      "clubs": [
        "CAG",
        "PAR"
      ]
    }
  ],
  "1992-04-05": [
    {
      "club_name": "Cagliari Calcio",
      "short_name": "CAG",
      "poin": 11,
      "score": 1
    },
    {
      "club_name": "AC Parma",
      "short_name": "PAR",
      "poin": 6,
      "score": 1
    },
    {
      "club_name": "Draw",
      "short_name": "DRAW",
      "poin": 12,
      "date": "1992-04-05",
      "time": "19:00",
      "result": "1:1",
      "league": "Serie A",
      "clubs": [
        "CAG",
        "PAR"
      ]
    }
  ],
  "1992-11-22": [
    {
      "club_name": "Cagliari Calcio",
      "short_name": "CAG",
      "poin": 11,
      "score": 0
    },
    {
      "club_name": "AC Parma",
      "short_name": "PAR",
      "poin": 7,
      "score": 1
    },
    {
      "club_name": "Draw",
      "short_name": "DRAW",
      "poin": 12,
      "date": "1992-11-22",
      "time": "19:00",
      "result": "0:1",
      "league": "Serie A",
      "clubs": [
        "CAG",
        "PAR"
      ]
    }
  ],
  "1993-04-10": [
    {
      "club_name": "Cagliari Calcio",
      "short_name": "CAG",
      "poin": 11,
      "score": 1
    },
    {
      "club_name": "AC Parma",
      "short_name": "PAR",
      "poin": 8,
      "score": 3
    },
    {
      "club_name": "Draw",
      "short_name": "DRAW",
      "poin": 12,
      "date": "1993-04-10",
      "time": "19:00",
      "result": "3:1",
      "league": "Serie A",
      "clubs": [
        "CAG",
        "PAR"
      ]
    }
  ],
  "1993-12-12": [
    {
      "club_name": "Cagliari Calcio",
      "short_name": "CAG",
      "poin": 11,
      "score": 0
    },
    {
      "club_name": "AC Parma",
      "short_name": "PAR",
      "poin": 9,
      "score": 4
    },
    {
      "club_name": "Draw",
      "short_name": "DRAW",
      "poin": 12,
      "date": "1993-12-12",
      "time": "19:00",
      "result": "0:4",
      "league": "Serie A",
      "clubs": [
        "CAG",
        "PAR"
      ]
    }
  ],
  "1994-04-17": [
    {
      "club_name": "Cagliari Calcio",
      "short_name": "CAG",
      "poin": 11,
      "score": 1
    },
    {
      "club_name": "AC Parma",
      "short_name": "PAR",
      "poin": 10,
      "score": 3
    },
    {
      "club_name": "Draw",
      "short_name": "DRAW",
      "poin": 12,
      "date": "1994-04-17",
      "time": "19:00",
      "result": "3:1",
      "league": "Serie A",
      "clubs": [
        "CAG",
        "PAR"
      ]
    }
  ],
  "1994-09-18": [
    {
      "club_name": "Cagliari Calcio",
      "short_name": "CAG",
      "poin": 11,
      "score": 1
    },
    {
      "club_name": "AC Parma",
      "short_name": "PAR",
      "poin": 11,
      "score": 2
    },
    {
      "club_name": "Draw",
      "short_name": "DRAW",
      "poin": 12,
      "date": "1994-09-18",
      "time": "19:00",
      "result": "2:1",
      "league": "Serie A",
      "clubs": [
        "CAG",
        "PAR"
      ]
    }
  ],
  "1994-10-12": [
    {
      "club_name": "Cagliari Calcio",
      "short_name": "CAG",
      "poin": 11,
      "score": 0
    },
    {
      "club_name": "AC Parma",
      "short_name": "PAR",
      "poin": 12,
      "score": 2
    },
    {
      "club_name": "Draw",
      "short_name": "DRAW",
      "poin": 12,
      "date": "1994-10-12",
      "time": "19:00",
      "result": "2:0",
      "league": "Italy Cup",
      "clubs": [
        "CAG",
        "PAR"
      ]
    }
  ],
  "1994-10-27": [
    {
      "club_name": "Cagliari Calcio",
      "short_name": "CAG",
      "poin": 11,
      "score": 1
    },
    {
      "club_name": "AC Parma",
      "short_name": "PAR",
      "poin": 12,
      "score": 1
    },
    {
      "club_name": "Draw",
      "short_name": "DRAW",
      "poin": 13,
      "date": "1994-10-27",
      "time": "19:00",
      "result": "1:1",
      "league": "Italy Cup",
      "clubs": [
        "CAG",
        "PAR"
      ]
    }
  ],
  "1995-02-19": [
    {
      "club_name": "Cagliari Calcio",
      "short_name": "CAG",
      "poin": 12,
      "score": 2
    },
    {
      "club_name": "AC Parma",
      "short_name": "PAR",
      "poin": 12,
      "score": 0
    },
    {
      "club_name": "Draw",
      "short_name": "DRAW",
      "poin": 13,
      "date": "1995-02-19",
      "time": "19:00",
      "result": "2:0",
      "league": "Serie A",
      "clubs": [
        "CAG",
        "PAR"
      ]
    }
  ],
  "1996-01-14": [
    {
      "club_name": "Cagliari Calcio",
      "short_name": "CAG",
      "poin": 12,
      "score": 0
    },
    {
      "club_name": "AC Parma",
      "short_name": "PAR",
      "poin": 13,
      "score": 4
    },
    {
      "club_name": "Draw",
      "short_name": "DRAW",
      "poin": 13,
      "date": "1996-01-14",
      "time": "19:00",
      "result": "4:0",
      "league": "Serie A",
      "clubs": [
        "CAG",
        "PAR"
      ]
    }
  ],
  "1996-05-12": [
    {
      "club_name": "Cagliari Calcio",
      "short_name": "CAG",
      "poin": 13,
      "score": 2
    },
    {
      "club_name": "AC Parma",
      "short_name": "PAR",
      "poin": 13,
      "score": 0
    },
    {
      "club_name": "Draw",
      "short_name": "DRAW",
      "poin": 13,
      "date": "1996-05-12",
      "time": "19:00",
      "result": "2:0",
      "league": "Serie A",
      "clubs": [
        "CAG",
        "PAR"
      ]
    }
  ],
  "1996-10-13": [
    {
      "club_name": "Cagliari Calcio",
      "short_name": "CAG",
      "poin": 13,
      "score": 0
    },
    {
      "club_name": "AC Parma",
      "short_name": "PAR",
      "poin": 14,
      "score": 1
    },
    {
      "club_name": "Draw",
      "short_name": "DRAW",
      "poin": 13,
      "date": "1996-10-13",
      "time": "19:00",
      "result": "0:1",
      "league": "Serie A",
      "clubs": [
        "CAG",
        "PAR"
      ]
    }
  ],
  "1997-03-02": [
    {
      "club_name": "Cagliari Calcio",
      "short_name": "CAG",
      "poin": 13,
      "score": 2
    },
    {
      "club_name": "AC Parma",
      "short_name": "PAR",
      "poin": 15,
      "score": 3
    },
    {
      "club_name": "Draw",
      "short_name": "DRAW",
      "poin": 13,
      "date": "1997-03-02",
      "time": "19:00",
      "result": "3:2",
      "league": "Serie A",
      "clubs": [
        "CAG",
        "PAR"
      ]
    }
  ],
  "1998-11-21": [
    {
      "club_name": "Cagliari Calcio",
      "short_name": "CAG",
      "poin": 14,
      "score": 1
    },
    {
      "club_name": "AC Parma",
      "short_name": "PAR",
      "poin": 15,
      "score": 0
    },
    {
      "club_name": "Draw",
      "short_name": "DRAW",
      "poin": 13,
      "date": "1998-11-21",
      "time": "08:30",
      "result": "1:0",
      "league": "Serie A",
      "clubs": [
        "CAG",
        "PAR"
      ]
    }
  ],
  "1999-04-03": [
    {
      "club_name": "Cagliari Calcio",
      "short_name": "CAG",
      "poin": 14,
      "score": 1
    },
    {
      "club_name": "AC Parma",
      "short_name": "PAR",
      "poin": 15,
      "score": 1
    },
    {
      "club_name": "Draw",
      "short_name": "DRAW",
      "poin": 14,
      "date": "1999-04-03",
      "time": "10:00",
      "result": "1:1",
      "league": "Serie A",
      "clubs": [
        "CAG",
        "PAR"
      ]
    }
  ],
  "1999-11-21": [
    {
      "club_name": "Cagliari Calcio",
      "short_name": "CAG",
      "poin": 14,
      "score": 1
    },
    {
      "club_name": "AC Parma",
      "short_name": "PAR",
      "poin": 16,
      "score": 3
    },
    {
      "club_name": "Draw",
      "short_name": "DRAW",
      "poin": 14,
      "date": "1999-11-21",
      "time": "09:00",
      "result": "3:1",
      "league": "Serie A",
      "clubs": [
        "CAG",
        "PAR"
      ]
    }
  ],
  "1999-12-01": [
    {
      "club_name": "Cagliari Calcio",
      "short_name": "CAG",
      "poin": 15,
      "score": 1
    },
    {
      "club_name": "AC Parma",
      "short_name": "PAR",
      "poin": 16,
      "score": 0
    },
    {
      "club_name": "Draw",
      "short_name": "DRAW",
      "poin": 14,
      "date": "1999-12-01",
      "time": "19:00",
      "result": "1:0",
      "league": "Italy Cup",
      "clubs": [
        "CAG",
        "PAR"
      ]
    }
  ],
  "1999-12-15": [
    {
      "club_name": "Cagliari Calcio",
      "short_name": "CAG",
      "poin": 15,
      "score": 2
    },
    {
      "club_name": "AC Parma",
      "short_name": "PAR",
      "poin": 16,
      "score": 2
    },
    {
      "club_name": "Draw",
      "short_name": "DRAW",
      "poin": 15,
      "date": "1999-12-15",
      "time": "19:00",
      "result": "2:2",
      "league": "Italy Cup",
      "clubs": [
        "CAG",
        "PAR"
      ]
    }
  ],
  "2000-03-25": [
    {
      "club_name": "Cagliari Calcio",
      "short_name": "CAG",
      "poin": 15,
      "score": 2
    },
    {
      "club_name": "AC Parma",
      "short_name": "PAR",
      "poin": 17,
      "score": 3
    },
    {
      "club_name": "Draw",
      "short_name": "DRAW",
      "poin": 15,
      "date": "2000-03-25",
      "time": "09:00",
      "result": "2:3",
      "league": "Serie A",
      "clubs": [
        "CAG",
        "PAR"
      ]
    }
  ],
  "2004-10-27": [
    {
      "club_name": "Cagliari Calcio",
      "short_name": "CAG",
      "poin": 16,
      "score": 2
    },
    {
      "club_name": "Parma FC",
      "short_name": "PAR",
      "poin": 17,
      "score": 1
    },
    {
      "club_name": "Draw",
      "short_name": "DRAW",
      "poin": 15,
      "date": "2004-10-27",
      "time": "14:30",
      "result": "2:1",
      "league": "Serie A",
      "clubs": [
        "CAG",
        "PAR"
      ]
    }
  ],
  "2005-03-06": [
    {
      "club_name": "Cagliari Calcio",
      "short_name": "CAG",
      "poin": 16,
      "score": 2
    },
    {
      "club_name": "Parma FC",
      "short_name": "PAR",
      "poin": 18,
      "score": 3
    },
    {
      "club_name": "Draw",
      "short_name": "DRAW",
      "poin": 15,
      "date": "2005-03-06",
      "time": "09:00",
      "result": "3:2",
      "league": "Serie A",
      "clubs": [
        "CAG",
        "PAR"
      ]
    }
  ],
  "2005-12-21": [
    {
      "club_name": "Cagliari Calcio",
      "short_name": "CAG",
      "poin": 16,
      "score": 0
    },
    {
      "club_name": "Parma FC",
      "short_name": "PAR",
      "poin": 19,
      "score": 1
    },
    {
      "club_name": "Draw",
      "short_name": "DRAW",
      "poin": 15,
      "date": "2005-12-21",
      "time": "14:30",
      "result": "1:0",
      "league": "Serie A",
      "clubs": [
        "CAG",
        "PAR"
      ]
    }
  ],
  "2006-04-30": [
    {
      "club_name": "Cagliari Calcio",
      "short_name": "CAG",
      "poin": 17,
      "score": 3
    },
    {
      "club_name": "Parma FC",
      "short_name": "PAR",
      "poin": 19,
      "score": 1
    },
    {
      "club_name": "Draw",
      "short_name": "DRAW",
      "poin": 15,
      "date": "2006-04-30",
      "time": "09:00",
      "result": "3:1",
      "league": "Serie A",
      "clubs": [
        "CAG",
        "PAR"
      ]
    }
  ],
  "2006-12-10": [
    {
      "club_name": "Cagliari Calcio",
      "short_name": "CAG",
      "poin": 17,
      "score": 0
    },
    {
      "club_name": "Parma FC",
      "short_name": "PAR",
      "poin": 19,
      "score": 0
    },
    {
      "club_name": "Draw",
      "short_name": "DRAW",
      "poin": 16,
      "date": "2006-12-10",
      "time": "09:00",
      "result": "0:0",
      "league": "Serie A",
      "clubs": [
        "CAG",
        "PAR"
      ]
    }
  ],
  "2007-04-29": [
    {
      "club_name": "Cagliari Calcio",
      "short_name": "CAG",
      "poin": 17,
      "score": 1
    },
    {
      "club_name": "Parma FC",
      "short_name": "PAR",
      "poin": 20,
      "score": 2
    },
    {
      "club_name": "Draw",
      "short_name": "DRAW",
      "poin": 16,
      "date": "2007-04-29",
      "time": "09:00",
      "result": "2:1",
      "league": "Serie A",
      "clubs": [
        "CAG",
        "PAR"
      ]
    }
  ],
  "2007-09-16": [
    {
      "club_name": "Cagliari Calcio",
      "short_name": "CAG",
      "poin": 17,
      "score": 1
    },
    {
      "club_name": "Parma FC",
      "short_name": "PAR",
      "poin": 20,
      "score": 1
    },
    {
      "club_name": "Draw",
      "short_name": "DRAW",
      "poin": 17,
      "date": "2007-09-16",
      "time": "14:30",
      "result": "1:1",
      "league": "Serie A",
      "clubs": [
        "CAG",
        "PAR"
      ]
    }
  ],
  "2008-02-10": [
    {
      "club_name": "Cagliari Calcio",
      "short_name": "CAG",
      "poin": 17,
      "score": 1
    },
    {
      "club_name": "Parma FC",
      "short_name": "PAR",
      "poin": 20,
      "score": 1
    },
    {
      "club_name": "Draw",
      "short_name": "DRAW",
      "poin": 18,
      "date": "2008-02-10",
      "time": "09:00",
      "result": "1:1",
      "league": "Serie A",
      "clubs": [
        "CAG",
        "PAR"
      ]
    }
  ],
  "2009-09-27": [
    {
      "club_name": "Cagliari Calcio",
      "short_name": "CAG",
      "poin": 18,
      "score": 2
    },
    {
      "club_name": "Parma FC",
      "short_name": "PAR",
      "poin": 20,
      "score": 0
    },
    {
      "club_name": "Draw",
      "short_name": "DRAW",
      "poin": 18,
      "date": "2009-09-27",
      "time": "09:00",
      "result": "0:2",
      "league": "Serie A",
      "clubs": [
        "CAG",
        "PAR"
      ]
    }
  ],
  "2010-02-21": [
    {
      "club_name": "Cagliari Calcio",
      "short_name": "CAG",
      "poin": 19,
      "score": 2
    },
    {
      "club_name": "Parma FC",
      "short_name": "PAR",
      "poin": 20,
      "score": 0
    },
    {
      "club_name": "Draw",
      "short_name": "DRAW",
      "poin": 18,
      "date": "2010-02-21",
      "time": "09:00",
      "result": "2:0",
      "league": "Serie A",
      "clubs": [
        "CAG",
        "PAR"
      ]
    }
  ],
  "2011-01-09": [
    {
      "club_name": "Cagliari Calcio",
      "short_name": "CAG",
      "poin": 20,
      "score": 2
    },
    {
      "club_name": "Parma FC",
      "short_name": "PAR",
      "poin": 20,
      "score": 1
    },
    {
      "club_name": "Draw",
      "short_name": "DRAW",
      "poin": 18,
      "date": "2011-01-09",
      "time": "09:00",
      "result": "1:2",
      "league": "Serie A",
      "clubs": [
        "CAG",
        "PAR"
      ]
    }
  ],
  "2011-05-22": [
    {
      "club_name": "Cagliari Calcio",
      "short_name": "CAG",
      "poin": 20,
      "score": 1
    },
    {
      "club_name": "Parma FC",
      "short_name": "PAR",
      "poin": 20,
      "score": 1
    },
    {
      "club_name": "Draw",
      "short_name": "DRAW",
      "poin": 19,
      "date": "2011-05-22",
      "time": "12:00",
      "result": "1:1",
      "league": "Serie A",
      "clubs": [
        "CAG",
        "PAR"
      ]
    }
  ],
  "2011-12-11": [
    {
      "club_name": "Cagliari Calcio",
      "short_name": "CAG",
      "poin": 20,
      "score": 0
    },
    {
      "club_name": "Parma FC",
      "short_name": "PAR",
      "poin": 20,
      "score": 0
    },
    {
      "club_name": "Draw",
      "short_name": "DRAW",
      "poin": 20,
      "date": "2011-12-11",
      "time": "09:00",
      "result": "0:0",
      "league": "Serie A",
      "clubs": [
        "CAG",
        "PAR"
      ]
    }
  ],
  "2012-04-21": [
    {
      "club_name": "Cagliari Calcio",
      "short_name": "CAG",
      "poin": 20,
      "score": 0
    },
    {
      "club_name": "Parma FC",
      "short_name": "PAR",
      "poin": 21,
      "score": 3
    },
    {
      "club_name": "Draw",
      "short_name": "DRAW",
      "poin": 20,
      "date": "2012-04-21",
      "time": "12:00",
      "result": "3:0",
      "league": "Serie A",
      "clubs": [
        "CAG",
        "PAR"
      ]
    }
  ],
  "2012-12-16": [
    {
      "club_name": "Cagliari Calcio",
      "short_name": "CAG",
      "poin": 20,
      "score": 1
    },
    {
      "club_name": "Parma FC",
      "short_name": "PAR",
      "poin": 22,
      "score": 4
    },
    {
      "club_name": "Draw",
      "short_name": "DRAW",
      "poin": 20,
      "date": "2012-12-16",
      "time": "09:00",
      "result": "4:1",
      "league": "Serie A",
      "clubs": [
        "CAG",
        "PAR"
      ]
    }
  ],
  "2013-05-08": [
    {
      "club_name": "Cagliari Calcio",
      "short_name": "CAG",
      "poin": 20,
      "score": 0
    },
    {
      "club_name": "Parma FC",
      "short_name": "PAR",
      "poin": 23,
      "score": 1
    },
    {
      "club_name": "Draw",
      "short_name": "DRAW",
      "poin": 20,
      "date": "2013-05-08",
      "time": "14:45",
      "result": "0:1",
      "league": "Serie A",
      "clubs": [
        "CAG",
        "PAR"
      ]
    }
  ],
  "2013-12-15": [
    {
      "club_name": "Cagliari Calcio",
      "short_name": "CAG",
      "poin": 20,
      "score": 0
    },
    {
      "club_name": "Parma FC",
      "short_name": "PAR",
      "poin": 23,
      "score": 0
    },
    {
      "club_name": "Draw",
      "short_name": "DRAW",
      "poin": 21,
      "date": "2013-12-15",
      "time": "09:00",
      "result": "0:0",
      "league": "Serie A",
      "clubs": [
        "CAG",
        "PAR"
      ]
    }
  ],
  "2014-04-27": [
    {
      "club_name": "Cagliari Calcio",
      "short_name": "CAG",
      "poin": 21,
      "score": 1
    },
    {
      "club_name": "Parma FC",
      "short_name": "PAR",
      "poin": 23,
      "score": 0
    },
    {
      "club_name": "Draw",
      "short_name": "DRAW",
      "poin": 21,
      "date": "2014-04-27",
      "time": "09:00",
      "result": "1:0",
      "league": "Serie A",
      "clubs": [
        "CAG",
        "PAR"
      ]
    }
  ],
  "2014-12-14": [
    {
      "club_name": "Cagliari Calcio",
      "short_name": "CAG",
      "poin": 21,
      "score": 0
    },
    {
      "club_name": "Parma FC",
      "short_name": "PAR",
      "poin": 23,
      "score": 0
    },
    {
      "club_name": "Draw",
      "short_name": "DRAW",
      "poin": 22,
      "date": "2014-12-14",
      "time": "09:00",
      "result": "0:0",
      "league": "Serie A",
      "clubs": [
        "CAG",
        "PAR"
      ]
    }
  ],
  "2015-01-14": [
    {
      "club_name": "Cagliari Calcio",
      "short_name": "CAG",
      "poin": 21,
      "score": 1
    },
    {
      "club_name": "Parma FC",
      "short_name": "PAR",
      "poin": 24,
      "score": 2
    },
    {
      "club_name": "Draw",
      "short_name": "DRAW",
      "poin": 22,
      "date": "2015-01-14",
      "time": "12:00",
      "result": "2:1",
      "league": "Italy Cup",
      "clubs": [
        "CAG",
        "PAR"
      ]
    }
  ],
  "2015-05-04": [
    {
      "club_name": "Cagliari Calcio",
      "short_name": "CAG",
      "poin": 22,
      "score": 4
    },
    {
      "club_name": "Parma FC",
      "short_name": "PAR",
      "poin": 24,
      "score": 0
    },
    {
      "club_name": "Draw",
      "short_name": "DRAW",
      "poin": 22,
      "date": "2015-05-04",
      "time": "14:45",
      "result": "4:0",
      "league": "Serie A",
      "clubs": [
        "CAG",
        "PAR"
      ]
    }
  ],
  "2018-09-22": [
    {
      "club_name": "Cagliari Calcio",
      "short_name": "CAG",
      "poin": 22,
      "score": 0
    },
    {
      "club_name": "Parma Calcio 1913",
      "short_name": "PAR",
      "poin": 25,
      "score": 2
    },
    {
      "club_name": "Draw",
      "short_name": "DRAW",
      "poin": 22,
      "date": "2018-09-22",
      "time": "09:00",
      "result": "2:0",
      "league": "Serie A",
      "clubs": [
        "CAG",
        "PAR"
      ]
    }
  ],
  "2019-02-16": [
    {
      "club_name": "Cagliari Calcio",
      "short_name": "CAG",
      "poin": 23,
      "score": 2
    },
    {
      "club_name": "Parma Calcio 1913",
      "short_name": "PAR",
      "poin": 25,
      "score": 1
    },
    {
      "club_name": "Draw",
      "short_name": "DRAW",
      "poin": 22,
      "date": "2019-02-16",
      "time": "12:00",
      "result": "2:1",
      "league": "Serie A",
      "clubs": [
        "CAG",
        "PAR"
      ]
    }
  ],
  "2019-09-15": [
    {
      "club_name": "Cagliari Calcio",
      "short_name": "CAG",
      "poin": 24,
      "score": 3
    },
    {
      "club_name": "Parma Calcio 1913",
      "short_name": "PAR",
      "poin": 25,
      "score": 1
    },
    {
      "club_name": "Draw",
      "short_name": "DRAW",
      "poin": 22,
      "date": "2019-09-15",
      "time": "09:00",
      "result": "1:3",
      "league": "Serie A",
      "clubs": [
        "CAG",
        "PAR"
      ]
    }
  ],
  "2020-02-01": [
    {
      "club_name": "Cagliari Calcio",
      "short_name": "CAG",
      "poin": 24,
      "score": 2
    },
    {
      "club_name": "Parma Calcio 1913",
      "short_name": "PAR",
      "poin": 25,
      "score": 2
    },
    {
      "club_name": "Draw",
      "short_name": "DRAW",
      "poin": 23,
      "date": "2020-02-01",
      "time": "12:00",
      "result": "2:2",
      "league": "Serie A",
      "clubs": [
        "CAG",
        "PAR"
      ]
    }
  ],
  "2020-12-16": [
    {
      "club_name": "Cagliari Calcio",
      "short_name": "CAG",
      "poin": 24,
      "score": 0
    },
    {
      "club_name": "Parma Calcio 1913",
      "short_name": "PAR",
      "poin": 25,
      "score": 0
    },
    {
      "club_name": "Draw",
      "short_name": "DRAW",
      "poin": 24,
      "date": "2020-12-16",
      "time": "14:45",
      "result": "0:0",
      "league": "Serie A",
      "clubs": [
        "CAG",
        "PAR"
      ]
    }
  ],
  "2021-04-17": [
    {
      "club_name": "Cagliari Calcio",
      "short_name": "CAG",
      "poin": 25,
      "score": 4
    },
    {
      "club_name": "Parma Calcio 1913",
      "short_name": "PAR",
      "poin": 25,
      "score": 3
    },
    {
      "club_name": "Draw",
      "short_name": "DRAW",
      "poin": 24,
      "date": "2021-04-17",
      "time": "14:45",
      "result": "4:3",
      "league": "Serie A",
      "clubs": [
        "CAG",
        "PAR"
      ]
    }
  ],
  "2022-12-03": [
    {
      "club_name": "Cagliari Calcio",
      "short_name": "CAG",
      "poin": 25,
      "score": 1
    },
    {
      "club_name": "Parma Calcio 1913",
      "short_name": "PAR",
      "poin": 25,
      "score": 1
    },
    {
      "club_name": "Draw",
      "short_name": "DRAW",
      "poin": 25,
      "date": "2022-12-03",
      "time": "12:00",
      "result": "1:1",
      "league": "Serie B",
      "clubs": [
        "CAG",
        "PAR"
      ]
    }
  ],
  "2023-04-22": [
    {
      "club_name": "Cagliari Calcio",
      "short_name": "CAG",
      "poin": 25,
      "score": 1
    },
    {
      "club_name": "Parma Calcio 1913",
      "short_name": "PAR",
      "poin": 26,
      "score": 2
    },
    {
      "club_name": "Draw",
      "short_name": "DRAW",
      "poin": 25,
      "date": "2023-04-22",
      "time": "08:00",
      "result": "2:1",
      "league": "Serie B",
      "clubs": [
        "CAG",
        "PAR"
      ]
    }
  ],
  "2023-05-30": [
    {
      "club_name": "Cagliari Calcio",
      "short_name": "CAG",
      "poin": 26,
      "score": 3
    },
    {
      "club_name": "Parma Calcio 1913",
      "short_name": "PAR",
      "poin": 26,
      "score": 2
    },
    {
      "club_name": "Draw",
      "short_name": "DRAW",
      "poin": 25,
      "date": "2023-05-30",
      "time": "14:30",
      "result": "3:2",
      "league": "Serie B Play-off",
      "clubs": [
        "CAG",
        "PAR"
      ]
    }
  ],
  "2023-06-03": [
    {
      "club_name": "Cagliari Calcio",
      "short_name": "CAG",
      "poin": 26,
      "score": 0
    },
    {
      "club_name": "Parma Calcio 1913",
      "short_name": "PAR",
      "poin": 26,
      "score": 0
    },
    {
      "club_name": "Draw",
      "short_name": "DRAW",
      "poin": 26,
      "date": "2023-06-03",
      "time": "14:30",
      "result": "0:0",
      "league": "Serie B Play-off",
      "clubs": [
        "CAG",
        "PAR"
      ]
    }
  ],
  "2024-09-30": [
    {
      "club_name": "Cagliari Calcio",
      "short_name": "CAG",
      "poin": 27,
      "score": 3
    },
    {
      "club_name": "Parma Calcio 1913",
      "short_name": "PAR",
      "poin": 26,
      "score": 2
    },
    {
      "club_name": "Draw",
      "short_name": "DRAW",
      "poin": 26,
      "date": "2024-09-30",
      "time": "14:45",
      "result": "2:3",
      "league": "Serie A",
      "clubs": [
        "CAG",
        "PAR"
      ]
    }
  ],
  "2025-02-09": [
    {
      "club_name": "Cagliari Calcio",
      "short_name": "CAG",
      "poin": 28,
      "score": 2
    },
    {
      "club_name": "Parma Calcio 1913",
      "short_name": "PAR",
      "poin": 26,
      "score": 1
    },
    {
      "club_name": "Draw",
      "short_name": "DRAW",
      "poin": 26,
      "date": "2025-02-09",
      "time": "09:00",
      "result": "2:1",
      "league": "Serie A",
      "clubs": [
        "CAG",
        "PAR"
      ]
    }
  ]
}